cmdorc-0.12.0.dist-info/METADATA
cmdorc-0.12.0.dist-info/WHEEL
cmdorc-0.12.0.dist-info/entry_points.txt
cmdorc-0.12.0.dist-info/licenses/LICENSE
cmdorc/__init__.py
cmdorc/command_config.py
cmdorc/command_executor.py
cmdorc/command_orchestrator.py
cmdorc/command_runtime.py
cmdorc/concurrency_policy.py
cmdorc/exceptions.py
cmdorc/history_loader.py
cmdorc/load_config.py
cmdorc/local_subprocess_executor.py
cmdorc/logging_config.py
cmdorc/metadata_parser.py
cmdorc/mock_executor.py
cmdorc/py.typed
cmdorc/run_handle.py
cmdorc/run_result.py
cmdorc/runtime_vars.py
cmdorc/trigger_engine.py
cmdorc/types.py
cmdorc/utils.py
cmdorc-0.12.0.dist-info/RECORD
