Metadata-Version: 2.1
Name: cmdorc
Version: 0.12.0
Summary: Async-first, trigger-driven shell command orchestrator for TUIs and agents
Keywords: async,orchestration,tui,command-runner,automation,triggers,devtools
Author-Email: eyecantell <paul@pneuma.solutions>
License: MIT
Classifier: Programming Language :: Python :: 3
Classifier: Programming Language :: Python :: 3 :: Only
Classifier: Programming Language :: Python :: 3.10
Classifier: Programming Language :: Python :: 3.11
Classifier: Programming Language :: Python :: 3.12
Classifier: Programming Language :: Python :: 3.13
Classifier: License :: OSI Approved :: MIT License
Classifier: Operating System :: OS Independent
Classifier: Intended Audience :: Developers
Classifier: Topic :: Software Development :: Libraries :: Python Modules
Classifier: Topic :: Utilities
Classifier: Development Status :: 4 - Beta
Classifier: Typing :: Typed
Project-URL: Homepage, https://github.com/eyecantell/cmdorc
Project-URL: Repository, https://github.com/eyecantell/cmdorc
Project-URL: Issues, https://github.com/eyecantell/cmdorc/issues
Project-URL: Documentation, https://github.com/eyecantell/cmdorc#readme
Requires-Python: >=3.10
Requires-Dist: tomli>=2.3.0; python_version < "3.11"
Provides-Extra: test
Requires-Dist: pytest>=8.4.2; extra == "test"
Requires-Dist: pytest-asyncio>=1.2.0; extra == "test"
Requires-Dist: pytest-cov>=7.0.0; extra == "test"
Requires-Dist: ruff>=0.14.7; extra == "test"
Provides-Extra: examples
Requires-Dist: watchdog>=3.0.0; extra == "examples"
Requires-Dist: textual>=0.47.0; extra == "examples"
Requires-Dist: rich>=13.0.0; extra == "examples"
